easyocr/__init__.py
easyocr/cli.py
easyocr/config.py
easyocr/craft.py
easyocr/craft_utils.py
easyocr/detection.py
easyocr/detection_db.py
easyocr/easyocr.py
easyocr/export.py
easyocr/imgproc.py
easyocr/recognition.py
easyocr/utils.py
easyocr/DBNet/DBNet.py
easyocr/DBNet/README.md
easyocr/DBNet/dcn_compiling_success
easyocr/DBNet/log.txt
easyocr/DBNet/assets/ops/dcn/__init__.py
easyocr/DBNet/assets/ops/dcn/deform_conv_cuda.cpython-38-x86_64-linux-gnu.so
easyocr/DBNet/assets/ops/dcn/deform_pool_cuda.cpython-38-x86_64-linux-gnu.so
easyocr/DBNet/assets/ops/dcn/setup.py
easyocr/DBNet/assets/ops/dcn/build/lib.linux-x86_64-3.8/deform_conv_cuda.cpython-38-x86_64-linux-gnu.so
easyocr/DBNet/assets/ops/dcn/build/lib.linux-x86_64-3.8/deform_pool_cuda.cpython-38-x86_64-linux-gnu.so
easyocr/DBNet/assets/ops/dcn/build/temp.linux-x86_64-3.8/.ninja_deps
easyocr/DBNet/assets/ops/dcn/build/temp.linux-x86_64-3.8/.ninja_log
easyocr/DBNet/assets/ops/dcn/build/temp.linux-x86_64-3.8/build.ninja
easyocr/DBNet/assets/ops/dcn/build/temp.linux-x86_64-3.8/src/deform_conv_cuda.o
easyocr/DBNet/assets/ops/dcn/build/temp.linux-x86_64-3.8/src/deform_conv_cuda_kernel.o
easyocr/DBNet/assets/ops/dcn/build/temp.linux-x86_64-3.8/src/deform_pool_cuda.o
easyocr/DBNet/assets/ops/dcn/build/temp.linux-x86_64-3.8/src/deform_pool_cuda_kernel.o
easyocr/DBNet/assets/ops/dcn/functions/__init__.py
easyocr/DBNet/assets/ops/dcn/functions/deform_conv.py
easyocr/DBNet/assets/ops/dcn/functions/deform_pool.py
easyocr/DBNet/assets/ops/dcn/modules/__init__.py
easyocr/DBNet/assets/ops/dcn/modules/deform_conv.py
easyocr/DBNet/assets/ops/dcn/modules/deform_pool.py
easyocr/DBNet/assets/ops/dcn/src/deform_conv_cuda.cpp
easyocr/DBNet/assets/ops/dcn/src/deform_conv_cuda_kernel.cu
easyocr/DBNet/assets/ops/dcn/src/deform_pool_cuda.cpp
easyocr/DBNet/assets/ops/dcn/src/deform_pool_cuda_kernel.cu
easyocr/DBNet/backbones/__init__.py
easyocr/DBNet/backbones/mobilenetv3.py
easyocr/DBNet/backbones/resnet.py
easyocr-1.6.1.dist-info/LICENSE
easyocr-1.6.1.dist-info/METADATA
easyocr-1.6.1.dist-info/WHEEL
easyocr-1.6.1.dist-info/entry_points.txt
easyocr-1.6.1.dist-info/top_level.txt
easyocr-1.6.1.dist-info/RECORD
